YunyingZengchangShizhanShoujiXiaoheiShuNiaogeBijiFix1/README.md
YunyingZengchangShizhanShoujiXiaoheiShuNiaogeBijiFix1/__init__.py
YunyingZengchangShizhanShoujiXiaoheiShuNiaogeBijiFix1/__main__.py
YunyingZengchangShizhanShoujiXiaoheiShuNiaogeBijiFix1/file.pdf
YunyingZengchangShizhanShoujiXiaoheiShuNiaogeBijiFix1/index.html
yunying_zengchang_shizhan_shouji_xiaohei_shu_niaoge_biji_fix1-2025.3.24.1.dist-info/METADATA
yunying_zengchang_shizhan_shouji_xiaohei_shu_niaoge_biji_fix1-2025.3.24.1.dist-info/WHEEL
yunying_zengchang_shizhan_shouji_xiaohei_shu_niaoge_biji_fix1-2025.3.24.1.dist-info/entry_points.txt
yunying_zengchang_shizhan_shouji_xiaohei_shu_niaoge_biji_fix1-2025.3.24.1.dist-info/top_level.txt
yunying_zengchang_shizhan_shouji_xiaohei_shu_niaoge_biji_fix1-2025.3.24.1.dist-info/RECORD
